[
    {
        "title": "Milenial dan Gen Z Jadi Investor Dominan Pasar Modal",
        "category": "Ekonomi",
        "publish_time": "12-08-2024 14:08",
        "news_link": "https://ekonomi.republika.co.id/berita/si3za5423/milenial-dan-gen-z-jadi-investor-dominan-pasar-modal"
    },
    {
        "title": "Terungkap! Alasan PKS Kaji Ulang Dukungan untuk Anies",
        "category": "Video",
        "publish_time": "12-08-2024 14:01",
        "news_link": "https://tv.republika.co.id/berita/si3y33467/terungkap-alasan-pks-kaji-ulang-dukungan-untuk-anies"
    },
    {
        "title": "Polres Cianjur Amankan Ratusan Knalpot Brong dan Miras",
        "category": "Rejabar",
        "publish_time": "12-08-2024 13:57",
        "news_link": "https://rejabar.republika.co.id/berita/si3yrq512/polres-cianjur-amankan-ratusan-knalpot-brong-dan-miras"
    },
    {
        "title": "Wow Keren! Ribuan Siswa di Depok Dapat Beasiswa Senilai Rp 10,7 Miliar",
        "category": "Network",
        "publish_time": "12-08-2024 13:45",
        "news_link": "https://ruzka.republika.co.id/edukasi/1674968787/wow-keren-ribuan-siswa-di-depok-dapat-beasiswa-senilai-rp-107-miliar"
    },
    {
        "title": "Dosen UNM, Jadi Orang Pertama dari Indonesia Sebagai KNIME Certified Trainer and Contribur",
        "category": "News",
        "publish_time": "12-08-2024 13:44",
        "news_link": "https://news.republika.co.id/berita/si3xrx423/dosen-unm-jadi-orang-pertama-dari-indonesia-sebagai-knime-certified-trainer-and-contribur"
    },
    {
        "title": "Inovasi Pertamina di Juanda Diyakini Tingkatkan Efisiensi dan Keandalan Layanan Avtur",
        "category": "Ekonomi",
        "publish_time": "12-08-2024 13:43",
        "news_link": "https://ekonomi.republika.co.id/berita/si3y5y349/inovasi-pertamina-di-juanda-diyakini-tingkatkan-efisiensi-dan-keandalan-layanan-avtur"
    },
    {
        "title": "Ini Daftar Negara Beri Hadiah Terbesar Buat Peraih Medali Olimpiade, RI Kalahkan Malaysia",
        "category": "News",
        "publish_time": "12-08-2024 13:32",
        "news_link": "https://news.republika.co.id/berita/si3xmf377/ini-daftar-negara-beri-hadiah-terbesar-buat-peraih-medali-olimpiade-ri-kalahkan-malaysia"
    },
    {
        "title": "Komunitas Petani Depok Sejahtera Ajak Masyarakat Pilah Sampah Organik",
        "category": "Network",
        "publish_time": "12-08-2024 13:29",
        "news_link": "https://ruzka.republika.co.id/komunitas/1674968732/komunitas-petani-depok-sejahtera-ajak-masyarakat-pilah-sampah-organik"
    },
    {
        "title": "What? Nabi Adam Bukan Manusia Purba, Rahasia di Balik Arkeologi Alquran",
        "category": "Video",
        "publish_time": "12-08-2024 13:28",
        "news_link": "https://tv.republika.co.id/berita/si3xfj467/what-nabi-adam-bukan-manusia-purba-rahasia-di-balik-arkeologi-alquran"
    },
    {
        "title": "Gelar Dies Natalis ke-23, Universitas Nusa Mandiri Fokus Capai Akreditasi Unggul",
        "category": "News",
        "publish_time": "12-08-2024 13:26",
        "news_link": "https://news.republika.co.id/berita/si3xdo423/gelar-dies-natalis-ke23-universitas-nusa-mandiri-fokus-capai-akreditasi-unggul"
    },
    {
        "title": "Para Guru Ngaji Berharap Program Insentif Terus Berlanjut, Dukungan Penuh untuk Kang DS",
        "category": "Rejabar",
        "publish_time": "12-08-2024 13:22",
        "news_link": "https://rejabar.republika.co.id/berita/si3x6r423/para-guru-ngaji-berharap-program-insentif-terus-berlanjut-dukungan-penuh-untuk-kang-ds"
    },
    {
        "title": "PKB Bicara Peluang Koalisi dengan PDIP Usung Anies, Apa Katanya?",
        "category": "News",
        "publish_time": "12-08-2024 13:21",
        "news_link": "https://news.republika.co.id/berita/si3x4g487/pkb-bicara-peluang-koalisi-dengan-pdip-usung-anies-apa-katanya"
    },
    {
        "title": "Ridwan Kamil Bantah Mundurnya Airlangga Terkait dengan Pencalonannya di Pilgub Jakarta",
        "category": "Rejabar",
        "publish_time": "12-08-2024 13:20",
        "news_link": "https://rejabar.republika.co.id/berita/si3x3j512/ridwan-kamil-bantah-mundurnya-airlangga-terkait-dengan-pencalonannya-di-pilgub-jakarta"
    },
    {
        "title": "Ancaman Hizbullah Kian Nyata, Bagaimana Israel Dapat Menyelamatkan Diri?",
        "category": "Khazanah",
        "publish_time": "12-08-2024 13:16",
        "news_link": "https://khazanah.republika.co.id/berita/si3ww5483/ancaman-hizbullah-kian-nyata-bagaimana-israel-dapat-menyelamatkan-diri"
    },
    {
        "title": "Airlangga Terdepak dari Golkar, PKB Yakin Aman dari Intervensi",
        "category": "News",
        "publish_time": "12-08-2024 13:13",
        "news_link": "https://news.republika.co.id/berita/si3wrj487/airlangga-terdepak-dari-golkar-pkb-yakin-aman-dari-intervensi"
    },
    {
        "title": "Karhutla di Yunani Meluas",
        "category": "Esgnow",
        "publish_time": "12-08-2024 13:13",
        "news_link": "https://esgnow.republika.co.id/berita/si3wqi416/karhutla-di-yunani-meluas"
    },
    {
        "title": "PKB Undang Secara Personal Tokoh NU di Muktamar",
        "category": "News",
        "publish_time": "12-08-2024 13:12",
        "news_link": "https://news.republika.co.id/berita/si3woh377/pkb-undang-secara-personal-tokoh-nu-di-muktamar"
    },
    {
        "title": "Warga Antusias Ikuti 'Ngadandanan' Pasar BTM Cicadas",
        "category": "Rejabar",
        "publish_time": "12-08-2024 13:12",
        "news_link": "https://rejabar.republika.co.id/berita/si3wkx371/warga-antusias-ikuti-ngadandanan-pasar-btm-cicadas"
    },
    {
        "title": "Ace: Pengunduran Diri Airlangga Hartarto Sebagai Ketum Golkar Dilakukan Tanpa Tekanan",
        "category": "News",
        "publish_time": "12-08-2024 13:12",
        "news_link": "https://news.republika.co.id/berita/si3w6b377/ace-pengunduran-diri-airlangga-hartarto-sebagai-ketum-golkar-dilakukan-tanpa-tekanan"
    },
    {
        "title": "Ini Peran Strategis Petani Muda Masa Kini",
        "category": "Ekonomi",
        "publish_time": "12-08-2024 13:12",
        "news_link": "https://ekonomi.republika.co.id/berita/si3orz451/ini-peran-strategis-petani-muda-masa-kini"
    },
    {
        "title": "Bahlil Bicara Pengunduran Diri Airlangga: Saya Sama Dia Sahabat Baik",
        "category": "News",
        "publish_time": "12-08-2024 13:12",
        "news_link": "https://news.republika.co.id/berita/si3w3h487/bahlil-bicara-pengunduran-diri-airlangga-saya-sama-dia-sahabat-baik"
    },
    {
        "title": "Bawaslu Temukan Data Pemilih Fiktif di DPS Pilkada 2024 Majalengka",
        "category": "Rejabar",
        "publish_time": "12-08-2024 13:12",
        "news_link": "https://rejabar.republika.co.id/berita/si3w0w512/bawaslu-temukan-data-pemilih-fiktif-di-dps-pilkada-2024-majalengka"
    },
    {
        "title": "Demi Subisidi Tepat Sasaran, Ini Proses Pertamina Mendata Transaksi Pengguna Pertalite",
        "category": "Ekonomi",
        "publish_time": "12-08-2024 13:12",
        "news_link": "https://ekonomi.republika.co.id/berita/si3w0k490/demi-subisidi-tepat-sasaran-ini-proses-pertamina-mendata-transaksi-pengguna-pertalite"
    },
    {
        "title": "Terdakwa Pembunuh Empat Anak Kandung di Jagakarsa Dituntut Hukuman Mati",
        "category": "News",
        "publish_time": "12-08-2024 13:12",
        "news_link": "https://news.republika.co.id/berita/si3vyg409/terdakwa-pembunuh-empat-anak-kandung-di-jagakarsa-dituntut-hukuman-mati"
    },
    {
        "title": "PKB Undang Pimpinan Parpol di Muktamar ke-6, Pengurus PBNU Diundang?",
        "category": "News",
        "publish_time": "12-08-2024 13:12",
        "news_link": "https://news.republika.co.id/berita/si3vji377/pkb-undang-pimpinan-parpol-di-muktamar-ke6-pengurus-pbnu-diundang"
    },
    {
        "title": "Rully Rozano Jelaskan Pernyataan Kontroversial Ratakan Sulsel dengan Rp 50 Miliar",
        "category": "News",
        "publish_time": "12-08-2024 13:12",
        "news_link": "https://news.republika.co.id/berita/si3vfj484/rully-rozano-jelaskan-pernyataan-kontroversial-ratakan-sulsel-dengan-rp-50-miliar"
    },
    {
        "title": "PT SIE Dukung Peningkatan Produksi Migas Berbasis ESG",
        "category": "Esgnow",
        "publish_time": "12-08-2024 12:12",
        "news_link": "https://esgnow.republika.co.id/berita/si3v4p371/pt-sie-dukung-peningkatan-produksi-migas-berbasis-esg"
    },
    {
        "title": "Malaysia Gagal Lagi Dapat Emas Olimpiade, Atlet Dirundung, Anwar Ibrahim Angkat Bicara",
        "category": "News",
        "publish_time": "12-08-2024 12:12",
        "news_link": "https://news.republika.co.id/berita/si3uyp377/malaysia-gagal-lagi-dapat-emas-olimpiade-atlet-dirundung-anwar-ibrahim-angkat-bicara"
    },
    {
        "title": "Pakar: Label Bahaya BPA Wajib, Kesehatan Taruhannya",
        "category": "Ameera",
        "publish_time": "12-08-2024 12:12",
        "news_link": "https://ameera.republika.co.id/berita/si3pvk423/pakar-label-bahaya-bpa-wajib-kesehatan-taruhannya"
    },
    {
        "title": "Pilkada Depok 2024, KPU Tetapkan Ada 1,4 Juta Pemilih",
        "category": "Network",
        "publish_time": "12-08-2024 12:12",
        "news_link": "https://ruzka.republika.co.id/nasional/1674968496/pilkada-depok-2024-kpu-tetapkan-ada-14-juta-pemilih"
    },
    {
        "title": "Pengacara Saka Tatal Ungkap Hasil Ekstraksi Chat di HP Vina, Yakin PK Diterima MA",
        "category": "News",
        "publish_time": "12-08-2024 12:12",
        "news_link": "https://news.republika.co.id/berita/si3ugh409/pengacara-saka-tatal-ungkap-hasil-ekstraksi-chat-di-hp-vina-yakin-pk-diterima-ma"
    },
    {
        "title": "Perempuan Jadi Imam Shalat, Bolehkah Suaranya Dikeraskan?",
        "category": "Khazanah",
        "publish_time": "12-08-2024 12:12",
        "news_link": "https://www.republika.id/posts/54238/perempuan-jadi-imam-shalat-bolehkah-suaranya-dikeraskan"
    },
    {
        "title": "Presiden Potong Jumlah Undangan HUT RI di IKN, ini Penyebabnya",
        "category": "News",
        "publish_time": "12-08-2024 12:12",
        "news_link": "https://news.republika.co.id/berita/si3oo2451/presiden-potong-jumlah-undangan-hut-ri-di-ikn-ini-penyebabnya"
    },
    {
        "title": "Bagaimana Nasib Pencalonan Ridwan Kamil di Pilgub Jakarta Usai Airlangga Mundur?",
        "category": "News",
        "publish_time": "12-08-2024 12:12",
        "news_link": "https://news.republika.co.id/berita/si3txo409/bagaimana-nasib-pencalonan-ridwan-kamil-di-pilgub-jakarta-usai-airlangga-mundur"
    },
    {
        "title": "Diaspora Indonesia Berhasil Jajakan Kopi Alpukat di AS",
        "category": "Video",
        "publish_time": "12-08-2024 12:12",
        "news_link": "https://tv.republika.co.id/berita/si3tnb418/diaspora-indonesia-berhasil-jajakan-kopi-alpukat-di-as"
    },
    {
        "title": "Ini Respons Ridwan Kamil Soal Mundurnya Airlangga Hartarto dari Jabatan Ketum Golkar",
        "category": "News",
        "publish_time": "12-08-2024 12:12",
        "news_link": "https://news.republika.co.id/berita/si3tlq409/ini-respons-ridwan-kamil-soal-mundurnya-airlangga-hartarto-dari-jabatan-ketum-golkar"
    },
    {
        "title": "Kejagung: Kalau Ada Pemanggilan Terhadap Airlangga Hartarto Pasti akan Diumumkan",
        "category": "News",
        "publish_time": "12-08-2024 12:12",
        "news_link": "https://news.republika.co.id/berita/si3tgw377/kejagung-kalau-ada-pemanggilan-terhadap-airlangga-hartarto-pasti-akan-diumumkan"
    },
    {
        "title": "Meraih Untung dari Kerajinan Rajut",
        "category": "Visual",
        "publish_time": "12-08-2024 12:12",
        "news_link": "https://visual.republika.co.id/berita/si3q5p375/meraih-untung-dari-kerajinan-rajut"
    },
    {
        "title": "Menantang Masa Depan, Civitas Akademika\u00a0UNM Pamerkan Prestasi dan Integritas Diri",
        "category": "News",
        "publish_time": "12-08-2024 12:12",
        "news_link": "https://news.republika.co.id/berita/si3t81423/menantang-masa-depan-civitas-akademikaunm-pamerkan-prestasi-dan-integritas-diri"
    },
    {
        "title": "Bahlil Ungkap Empat Perusahaan Asing akan Berinvestasi di IKN",
        "category": "Ekonomi",
        "publish_time": "12-08-2024 12:12",
        "news_link": "https://ekonomi.republika.co.id/berita/si3t7j416/bahlil-ungkap-empat-perusahaan-asing-akan-berinvestasi-di-ikn"
    },
    {
        "title": "Pemimpin Barat Kelimpungan Cegah Iran Serang Israel",
        "category": "News",
        "publish_time": "12-08-2024 12:12",
        "news_link": "https://news.republika.co.id/berita/si3t1c393/pemimpin-barat-kelimpungan-cegah-iran-serang-israel"
    },
    {
        "title": "Bea Cukai Tingkatkan Pelayanan Lewat Program Customs Visit Customer",
        "category": "Beacukai",
        "publish_time": "12-08-2024 12:12",
        "news_link": "https://republika.co.id/berita/si3svk423/bea-cukai-tingkatkan-pelayanan-lewat-program-customs-visit-customer"
    },
    {
        "title": "Universitas BSI: AI, Kunci Masa Depan Pendidikan Indonesia",
        "category": "News",
        "publish_time": "12-08-2024 12:12",
        "news_link": "https://news.republika.co.id/berita/si3snl423/universitas-bsi-ai-kunci-masa-depan-pendidikan-indonesia"
    },
    {
        "title": "Butuh 4.5 Jam Untuk Padamkan Api Kebakaran KM Kirana I",
        "category": "Network",
        "publish_time": "12-08-2024 11:12",
        "news_link": "https://matapantura.republika.co.id/posts/324457/butuh-4-5-jam-untuk-padamkan-api-kebakaran-km-kirana-i"
    },
    {
        "title": "Pantang Menyerah! Relawan MER-C di Gaza Tetap Layani Pasien",
        "category": "Khazanah",
        "publish_time": "12-08-2024 11:12",
        "news_link": "https://khazanah.republika.co.id/berita/si3sfu458/pantang-menyerah-relawan-merc-di-gaza-tetap-layani-pasien"
    },
    {
        "title": "VYN Pindah Divisi, Siap Memulai Scene Kompetitif HOK Bersama RRQ",
        "category": "Network",
        "publish_time": "12-08-2024 11:12",
        "news_link": "https://foreveresports.id/posts/324409/vyn-pindah-divisi-siap-memulai-scene-kompetitif-hok-bersama-rrq"
    },
    {
        "title": "Funso Suguhkan Sensasi Baru Nikmati Ubi dalam Ragam Menu Modern",
        "category": "Ameera",
        "publish_time": "12-08-2024 11:12",
        "news_link": "https://ameera.republika.co.id/berita/si3s7s425/funso-suguhkan-sensasi-baru-nikmati-ubi-dalam-ragam-menu-modern"
    },
    {
        "title": "TC Timnas U-17 Digelar di Bali, Nova Arianto Bawa 35 Pemain",
        "category": "News",
        "publish_time": "12-08-2024 11:12",
        "news_link": "https://news.republika.co.id/berita/si3s5y348/tc-timnas-u17-digelar-di-bali-nova-arianto-bawa-35-pemain"
    },
    {
        "title": "Misteri Kekuatan Besar di Belakang Airlangga Mundur, Pengamat: Ada Politik Tingkat Tinggi",
        "category": "News",
        "publish_time": "12-08-2024 11:12",
        "news_link": "https://news.republika.co.id/berita/si3s5u377/misteri-kekuatan-besar-di-belakang-airlangga-mundur-pengamat-ada-politik-tingkat-tinggi"
    },
    {
        "title": "Wamen LHK RI Alue Dohong: Generasi Muda Jangan Lelah Lakukan Perbaikan Lingkungan Hidup",
        "category": "Network",
        "publish_time": "12-08-2024 11:12",
        "news_link": "https://cari.republika.co.id/posts/324456/wamen-lhk-ri-alue-dohong-generasi-muda-jangan-lelah-lakukan-perbaikan-lingkungan-hidup"
    }
]