[
    {
        "title": "Pimpinan DPR Sebut Mayoritas Partai Sepakat tak Melakukan Revisi UU MD3",
        "category": "News",
        "publish_time": "04-04-2024 07:08"
    },
    {
        "title": "Hindari Penumpukan Kendaraan Pemudik, Menko PMK: Jangan Berlama-lama di Rest Area",
        "category": "News",
        "publish_time": "04-04-2024 07:03"
    },
    {
        "title": "Dompet Dhuafa Lepas 350 Penerima Manfaat untuk Mudik Gratis",
        "category": "Khazanah",
        "publish_time": "04-04-2024 07:00"
    },
    {
        "title": "Wapres Sebut Semboyan Kemajemukan Sulut Sejalan dengan Pengembangan Ekonomi Syariah",
        "category": "Sharia",
        "publish_time": "04-04-2024 06:59"
    },
    {
        "title": "Dorong Ketahanan Pangan, Jamkrindo Kolaborasi Program Kebun Gizi",
        "category": "Khazanah",
        "publish_time": "04-04-2024 06:55"
    },
    {
        "title": "Netanyahu Terus Digoyang Desakan Pemilu",
        "category": "Internasional",
        "publish_time": "04-04-2024 06:55"
    },
    {
        "title": "Pengamat Nilai Kebijakan Satu Arah Saat Mudik Baiknya tak Diterapkan",
        "category": "Video",
        "publish_time": "04-04-2024 06:54"
    },
    {
        "title": "Hingga Siang, Sebanyak 12 RT di Jakarta Masih Tergenang Banjir",
        "category": "News",
        "publish_time": "04-04-2024 06:52"
    },
    {
        "title": "Pria Bawa Senjata Airgun Ditangkap di Sleman, Polisi Ungkap Motifnya",
        "category": "Rejogja",
        "publish_time": "04-04-2024 06:51"
    },
    {
        "title": "Masyarakat Kini Dipaksa Semakin Hati-Hati dalam Hiruk-Pikuk Dunia Digital",
        "category": "Network",
        "publish_time": "04-04-2024 06:51"
    },
    {
        "title": "Penampakan Ruas Tol Bocimi yang Ambles",
        "category": "Visual",
        "publish_time": "04-04-2024 06:51"
    },
    {
        "title": "Kejagung Periksa Sandra Dewi, Telusuri Aliran Dana Hasil Korupsi",
        "category": "News",
        "publish_time": "04-04-2024 06:50"
    },
    {
        "title": "Nuthuk dan Parkir Liar pada Libur Lebaran Bakal Ditindak Tegas",
        "category": "Rejogja",
        "publish_time": "04-04-2024 06:48"
    },
    {
        "title": "Menhan Rusia dan Prancis Bahas Ukraina Lewat Sambungan Telepon",
        "category": "Internasional",
        "publish_time": "04-04-2024 06:48"
    },
    {
        "title": "Ramadhan Bersama BRI Life, Senantiasa Berbagi kepada Sesama",
        "category": "Ramadhan",
        "publish_time": "04-04-2024 06:48"
    },
    {
        "title": "Puan Pastikan Risma Siap Berikan Keterangan di MK",
        "category": "Pemilu Kita",
        "publish_time": "04-04-2024 06:43"
    },
    {
        "title": "Hadapi Arus Mudik Lebaran, BP Batam Optimalkan Pelayanan Penumpang",
        "category": "News",
        "publish_time": "04-04-2024 06:41"
    },
    {
        "title": "Mobil Terperosok di Bocimi, Komisi V: Operator Tol Harus Ganti Rugi",
        "category": "Ekonomi",
        "publish_time": "04-04-2024 06:39"
    },
    {
        "title": "Muhaimin: Erni Sugiyanti Kader Terbaik PKB",
        "category": "News",
        "publish_time": "04-04-2024 06:38"
    },
    {
        "title": "NASA Menciptakan 'Waktu Standar Bulan' dan Benda Langit Lainnya",
        "category": "Network",
        "publish_time": "04-04-2024 06:37"
    },
    {
        "title": "Tiket Argo Parahyangan ke Bandung dari Gambir Jumat 5 April, Ini Jadwalnya",
        "category": "Network",
        "publish_time": "04-04-2024 06:37"
    },
    {
        "title": "Sstt...Apple Sedang Mengembangkan Robot Pribadi Untuk Rumah Anda",
        "category": "Network",
        "publish_time": "04-04-2024 06:37"
    },
    {
        "title": "Inggris Khawatir Peredaran Narkoba 'Frankenstein' Bakal Picu Kematian Massal",
        "category": "Ameera",
        "publish_time": "04-04-2024 06:37"
    },
    {
        "title": "Makna Sejati di Balik Sujud dan Pengabdian",
        "category": "Retizen",
        "publish_time": "04-04-2024 06:35"
    },
    {
        "title": "Ups Salah, Sandra Dewi Bukan Dewi Sandra",
        "category": "Retizen",
        "publish_time": "04-04-2024 06:35"
    },
    {
        "title": "Yusril Heran dengan Gugatan PDIP ke PTUN, tak Hanya Mau Batalkan Pilpres Tapi Juga Pileg",
        "category": "News",
        "publish_time": "04-04-2024 06:31"
    },
    {
        "title": "Ahli Tata Negara Sebut MK tak Bisa Diskualifikasi Prabowo-Gibran",
        "category": "News",
        "publish_time": "04-04-2024 06:31"
    },
    {
        "title": "Agensi Pastikan G-Dragon Comeback Tahun Ini",
        "category": "Ameera",
        "publish_time": "04-04-2024 06:27"
    },
    {
        "title": "Sindir Hasto Soal Jokowi Ingin Ambil Alih PDIP, Gerindra: Baiknya Dibicarakan di Internal",
        "category": "News",
        "publish_time": "04-04-2024 06:23"
    },
    {
        "title": "Jasindo Syariah dan Amanah Takaful Salurkan Kado Bahagia Ramadhan Guru Ngaji",
        "category": "Ramadhan",
        "publish_time": "04-04-2024 06:23"
    },
    {
        "title": "PT Trans Jabar Upayakan Lajur Tol Bocimi yang Longsor Dapat Segera Diperbaiki",
        "category": "Ekonomi",
        "publish_time": "04-04-2024 06:19"
    },
    {
        "title": "Dua Pejalan Kaki dan Seorang Pengendara Motor Tewas Usai Terlibat Kecelakaan di Bandung",
        "category": "News",
        "publish_time": "04-04-2024 06:19"
    },
    {
        "title": "Tol Bocimi tak Bisa Dipakai untuk Arus Mudik, Perbaikan Butuh 2-3 Bulan",
        "category": "News",
        "publish_time": "04-04-2024 06:14"
    },
    {
        "title": "H-6, Stasiun Bandung Ramai Oleh Pemudik ke Jatim, Jateng dan DIY",
        "category": "Rejabar",
        "publish_time": "04-04-2024 06:12"
    },
    {
        "title": "Michael J Fox Apresiasi Penggemar yang Mendukungnya Lawan Penyakit Parkinson",
        "category": "Ameera",
        "publish_time": "04-04-2024 06:12"
    },
    {
        "title": "Geleng-Geleng Puan Ditanyai Hak Angket dari PDIP",
        "category": "News",
        "publish_time": "04-04-2024 06:09"
    },
    {
        "title": "Getty Images Kasih Catatan untuk Video Pengumuman Kanker Kate Middleton",
        "category": "Ameera",
        "publish_time": "04-04-2024 06:09"
    },
    {
        "title": "Bambang Widjojanto Walk Out saat Eddy Hiariej Beri Keterangan di MK",
        "category": "Pemilu Kita",
        "publish_time": "04-04-2024 06:09"
    },
    {
        "title": "KISS Menjual Katalog, Nama Merek dan IP Senilai Lebih Rp 4,5 Triliun",
        "category": "Network",
        "publish_time": "04-04-2024 06:09"
    },
    {
        "title": "Adele Umumkan Jadwal Ulang Pertunjukan Weekends With Adele di Las Vegas",
        "category": "Network",
        "publish_time": "04-04-2024 06:09"
    },
    {
        "title": "Eddy Hiariej 'Serang Balik' Bambang Widjojanto Singgung Belas Kasihan Jaksa Agung",
        "category": "News",
        "publish_time": "04-04-2024 06:09"
    },
    {
        "title": "Jalan Tol Bocimi KM 64 Longsor, Polisi Masih Berlakukan Pengalihan Arus Lalu Lintas",
        "category": "Network",
        "publish_time": "04-04-2024 06:09"
    },
    {
        "title": "SKYE GILA! Build Item Paling MEMATIKAN Bikin Lawan Nangis di Paladins!",
        "category": "Network",
        "publish_time": "04-04-2024 06:09"
    },
    {
        "title": "Dukungan 3 April Jadi Hari NKRI Bergema di Nginden, Kota Surabaya",
        "category": "Network",
        "publish_time": "04-04-2024 06:09"
    },
    {
        "title": "Tips Ketika Terjebak Gempa Saat di Dalam Mobil",
        "category": "Ameera",
        "publish_time": "04-04-2024 06:09"
    },
    {
        "title": "Mudik Lebaran, Ini Tips Bersafar Selamat Sampai Tujuan",
        "category": "Network",
        "publish_time": "04-04-2024 06:09"
    },
    {
        "title": "Puan Gelengkan Kepala Saat Ditanya Revisi UU MD3 dan Jokowi yang Ingin Ambil Alih PDIP",
        "category": "News",
        "publish_time": "04-04-2024 06:09"
    },
    {
        "title": "Pj Heru Batal Melepas Peserta Mudik Gratis, Sekda: Ada Alasan Kesehatan",
        "category": "News",
        "publish_time": "04-04-2024 06:09"
    },
    {
        "title": "Ketika Algoritma Dimanfaatkan untuk Genosida",
        "category": "Internasional",
        "publish_time": "04-04-2024 06:09"
    },
    {
        "title": "IHATEC Gelar Pelatihan Auditor Halal Berbasis Kompetensi untuk Lembaga Sertifikasi Halal Asing",
        "category": "Network",
        "publish_time": "04-04-2024 06:09"
    }
]